pytimedinput/__init__.py
pytimedinput/__version__.py
pytimedinput/pytimedinput.py
pytimedinput-2.0.0.dist-info/LICENSE
pytimedinput-2.0.0.dist-info/WHEEL
pytimedinput-2.0.0.dist-info/METADATA
pytimedinput-2.0.0.dist-info/RECORD
