Metadata-Version: 2.1
Name: pytimedinput
Version: 2.0.0
Summary: Query a user for input with a timeout.
Home-page: https://github.com/werecatf/pytimedinput/
License: MIT
Keywords: Text-input,Shell,Interactive,Keyboard,Input
Author: WereCatf
Author-email: werecatf@runbox.com
Maintainer: WereCatf
Maintainer-email: werecatf@runbox.com
Requires-Python: >=3.6,<4.0
Classifier: License :: OSI Approved :: MIT License
Classifier: Programming Language :: Python :: 3
Classifier: Programming Language :: Python :: 3.10
Classifier: Programming Language :: Python :: 3.6
Classifier: Programming Language :: Python :: 3.7
Classifier: Programming Language :: Python :: 3.8
Classifier: Programming Language :: Python :: 3.9
Requires-Dist: colorama; sys_platform == "win32"
Project-URL: Repository, https://github.com/werecatf/pytimedinput/
Project-URL: issues, https://github.com/werecatf/pytimedinput/issues
